hct_mcp_signals/__init__.py
hct_mcp_signals/factory.py
hct_mcp_signals/json_schema.py
hct_mcp_signals/py.typed
hct_mcp_signals/schema.py
hct_mcp_signals/mcp/__init__.py
hct_mcp_signals-0.8.0.dist-info/METADATA
hct_mcp_signals-0.8.0.dist-info/WHEEL
hct_mcp_signals-0.8.0.dist-info/licenses/LICENSE
hct_mcp_signals-0.8.0.dist-info/RECORD
